pydracor_base/__init__.py
pydracor_base/api_client.py
pydracor_base/api_response.py
pydracor_base/configuration.py
pydracor_base/exceptions.py
pydracor_base/py.typed
pydracor_base/rest.py
pydracor_base/api/__init__.py
pydracor_base/api/admin_api.py
pydracor_base/api/dts_api.py
pydracor_base/api/public_api.py
pydracor_base/api/webhook_api.py
pydracor_base/api/wikidata_api.py
pydracor_base/models/__init__.py
pydracor_base/models/author_in_play_in_corpus.py
pydracor_base/models/author_in_play_metadata.py
pydracor_base/models/character.py
pydracor_base/models/character_in_play_metadata.py
pydracor_base/models/corpus.py
pydracor_base/models/corpus_in_corpora.py
pydracor_base/models/corpus_metrics.py
pydracor_base/models/dts_entrypoint.py
pydracor_base/models/external_reference_resource_id.py
pydracor_base/models/info.py
pydracor_base/models/load_corpus_request.py
pydracor_base/models/node_in_play_metrics.py
pydracor_base/models/play.py
pydracor_base/models/play_in_corpus.py
pydracor_base/models/play_metadata.py
pydracor_base/models/play_metrics.py
pydracor_base/models/play_with_wikidata_character.py
pydracor_base/models/post_corpora_request.py
pydracor_base/models/relation_item_in_play_metadata.py
pydracor_base/models/segment_item_in_play_metadata.py
pydracor_base/models/source_in_play_metadata.py
pydracor_base/models/spoken_text_by_character.py
pydracor_base/models/wikidata_author_info404_response.py
pydracor_base/models/word_counts.py
pydracor_base-1.0.1.dist-info/licenses/LICENCE
pydracor_base-1.0.1.dist-info/METADATA
pydracor_base-1.0.1.dist-info/WHEEL
pydracor_base-1.0.1.dist-info/top_level.txt
pydracor_base-1.0.1.dist-info/RECORD
