Metadata-Version: 2.4
Name: pydracor-base
Version: 1.0.1
Summary: DraCor API
Home-page: https://github.com/dracor-org/pydracor-base
Author: OpenAPI Generator community, Henny Sluyter-Gäthje
Author-email: sluytergaeth@uni-potsdam.de
License: MIT
Keywords: OpenAPI,OpenAPI-Generator,DraCor API,Wrapper
License-File: LICENCE
Requires-Dist: urllib3<3.0.0,>=1.25.3
Requires-Dist: python-dateutil>=2.8.2
Requires-Dist: pydantic>=2
Requires-Dist: typing-extensions>=4.7.1
Dynamic: author
Dynamic: author-email
Dynamic: description
Dynamic: description-content-type
Dynamic: home-page
Dynamic: keywords
Dynamic: license
Dynamic: license-file
Dynamic: requires-dist
Dynamic: summary
